mix_n_match/__init__.py
mix_n_match/correlations.py
mix_n_match/main.py
mix_n_match/utils.py
mix_n_match-0.4.0.dist-info/LICENSE
mix_n_match-0.4.0.dist-info/METADATA
mix_n_match-0.4.0.dist-info/WHEEL
mix_n_match-0.4.0.dist-info/top_level.txt
mix_n_match-0.4.0.dist-info/RECORD
