Metadata-Version: 2.1
Name: mix-n-match
Version: 0.4.0
Summary: Package for dataframe processing
Home-page: https://github.com/namiyousef/mix-n-match
Author: Yousef Nami
Author-email: namiyousef@hotmail.com
License: MIT
License-File: LICENSE
Requires-Dist: polars
Requires-Dist: scikit-learn
Provides-Extra: test
Requires-Dist: pytest ; extra == 'test'
Requires-Dist: pre-commit ; extra == 'test'
Requires-Dist: coverage ; extra == 'test'
Requires-Dist: python-dateutil ; extra == 'test'
